cis_checks_6/__init__.py
cis_checks_6/iam_control_1.py
cis_checks_6/logging_control_2.py
cis_checks_6/monitoring_control_3.py
cis_checks_6/networking_control_4.py
cis_checks_6/security_control_5.py
cis_checks_6/utils.py
cis_checks_6-0.0.7.dist-info/METADATA
cis_checks_6-0.0.7.dist-info/WHEEL
cis_checks_6-0.0.7.dist-info/top_level.txt
cis_checks_6-0.0.7.dist-info/RECORD
